README.rst
requirements.txt
setup.py
test/test_http_client.py
test/test_mongo_client.py
tomato/__init__.py
tomato/store/__init__.py
tomato/store/leveldb.py
tomato/store/mongo/__init__.py
tomato/store/mongo/mongo_client.py
tomato/store/mongo/mongo_helper.py
tomato/store/mysql/__init__.py
tomato/store/mysql/mysql_batch_controller.py
tomato/store/mysql/mysql_controller.py
tomato/store/mysql/mysql_model.py
tomato/store/mysql/mysql_module.py
tomato/store/mysql/sql_clause_assemble.py
tomato/store/mysql/sql_param_collections.py
tomato/store/redis/__init__.py
tomato/store/redis/redis_controller.py
tomato/store/redis/redis_module.py
tomato/transport/__init__.py
tomato/transport/http/__init__.py
tomato/transport/http/http_client.py
tomato/transport/http/http_server_module.py
tomato/transport/http/index_html.py
tomato/transport/http/routes.py
tomato/util/__init__.py
tomato/util/application.py
tomato/util/appmodule.py
tomato/util/log.py
tomato/util/singleton.py
tomato/util/typeassert.py
tomatolib.egg-info/PKG-INFO
tomatolib.egg-info/SOURCES.txt
tomatolib.egg-info/dependency_links.txt
tomatolib.egg-info/requires.txt
tomatolib.egg-info/top_level.txt