Metadata-Version: 2.1
Name: tomatolib
Version: 0.4.5
Summary: A quick and lightweight server framework.
Home-page: https://github.com/tangmi001/tomatolib
Author: tangmi
Author-email: tangmi360@gmail.com
Maintainer: tangmi <tangmi360@gmail.com>, stevenhu <love.as.string@gmail.com>
Maintainer-email: tomatolibs@gmail.com
License: GNU General Public License v3
Keywords: tomatolib,tomato
Platform: UNKNOWN
Classifier: License :: OSI Approved :: GNU General Public License v3 (GPLv3)
Classifier: Intended Audience :: Developers
Classifier: Programming Language :: Python
Classifier: Programming Language :: Python :: 3
Classifier: Programming Language :: Python :: 3.5
Classifier: Programming Language :: Python :: 3.6
Classifier: Programming Language :: Python :: 3.7
Classifier: Development Status :: 5 - Production/Stable
Classifier: Operating System :: POSIX
Classifier: Operating System :: MacOS :: MacOS X
Classifier: Operating System :: Microsoft :: Windows
Classifier: Topic :: Internet :: WWW/HTTP
Classifier: Framework :: AsyncIO
Requires-Python: >=3.5.3
